marlin_data/__init__.py
marlin_data/marlin_data.py
marlin_data/test.py
marlin_data/test_sims.py
marlin_data-14.2.0.dist-info/licenses/LICENSE
marlin_data-14.2.0.dist-info/METADATA
marlin_data-14.2.0.dist-info/WHEEL
marlin_data-14.2.0.dist-info/top_level.txt
marlin_data-14.2.0.dist-info/RECORD
