Metadata-Version: 2.4
Name: marlin_data
Version: 14.2.0
Summary: Marlin Learn | Framework Data Adapter
Author: Rahul Tandon
Author-email: r.tandon@rsaqua.co.uk
Classifier: Programming Language :: Python :: 3
Classifier: License :: OSI Approved :: MIT License
Classifier: Operating System :: OS Independent
Requires-Python: >=3.7
License-File: LICENSE
Dynamic: author
Dynamic: author-email
Dynamic: classifier
Dynamic: description
Dynamic: description-content-type
Dynamic: license-file
Dynamic: requires-python
Dynamic: summary
